{"_id":"grunt-parallel","_rev":"19-5d546d1018b6c705cd5f8b7e5e478ea7","name":"grunt-parallel","description":"Run tasks or commands in child processes.","dist-tags":{"latest":"0.4.1"},"versions":{"0.0.1":{"name":"grunt-parallel","description":"Run tasks or commands in child processes.","version":"0.0.1","homepage":"https://github.com/iammerrick/grunt-parallel","author":{"name":"Merrick Christensen","email":"merrick.christensen@gmail.com","url":"http://merrickchristensen.com"},"repository":{"type":"git","url":"git://github.com/iammerrick/grunt-parallel.git"},"bugs":{"url":"https://github.com/iammerrick/grunt-parallel/issues"},"licenses":[{"type":"MIT","url":"https://github.com/iammerrick/grunt-parallel/blob/master/LICENSE-MIT"}],"main":"Gruntfile.js","engines":{"node":"*"},"devDependencies":{"grunt":"~0.4.0"},"keywords":["gruntplugin","parallel"],"dependencies":{"q":"~0.8.12"},"_id":"grunt-parallel@0.0.1","dist":{"shasum":"4de1c9e397cf4c3f0cc25f13395735fd6b0cc523","tarball":"http://registry.npmjs.org/grunt-parallel/-/grunt-parallel-0.0.1.tgz"},"_npmVersion":"1.1.66","_npmUser":{"name":"iammerrick","email":"merrick.christensen@gmail.com"},"maintainers":[{"name":"iammerrick","email":"merrick.christensen@gmail.com"}],"directories":{}},"0.0.2":{"name":"grunt-parallel","description":"Run tasks or commands in child processes.","version":"0.0.2","homepage":"https://github.com/iammerrick/grunt-parallel","author":{"name":"Merrick Christensen","email":"merrick.christensen@gmail.com","url":"http://merrickchristensen.com"},"repository":{"type":"git","url":"git://github.com/iammerrick/grunt-parallel.git"},"bugs":{"url":"https://github.com/iammerrick/grunt-parallel/issues"},"licenses":[{"type":"MIT","url":"https://github.com/iammerrick/grunt-parallel/blob/master/LICENSE-MIT"}],"main":"Gruntfile.js","engines":{"node":"*"},"devDependencies":{"grunt":"~0.4.0"},"keywords":["gruntplugin","parallel"],"dependencies":{"q":"~0.8.12"},"_id":"grunt-parallel@0.0.2","dist":{"shasum":"699435f658948880321335b44911f916c3f34a0f","tarball":"http://registry.npmjs.org/grunt-parallel/-/grunt-parallel-0.0.2.tgz"},"_npmVersion":"1.1.66","_npmUser":{"name":"iammerrick","email":"merrick.christensen@gmail.com"},"maintainers":[{"name":"iammerrick","email":"merrick.christensen@gmail.com"}],"directories":{}},"0.0.3":{"name":"grunt-parallel","description":"Run tasks or commands in child processes.","version":"0.0.3","homepage":"https://github.com/iammerrick/grunt-parallel","author":{"name":"Merrick Christensen","email":"merrick.christensen@gmail.com","url":"http://merrickchristensen.com"},"repository":{"type":"git","url":"git://github.com/iammerrick/grunt-parallel.git"},"bugs":{"url":"https://github.com/iammerrick/grunt-parallel/issues"},"licenses":[{"type":"MIT","url":"https://github.com/iammerrick/grunt-parallel/blob/master/LICENSE-MIT"}],"main":"Gruntfile.js","engines":{"node":"*"},"devDependencies":{"grunt":"~0.4.0"},"keywords":["gruntplugin","parallel"],"dependencies":{"q":"~0.8.12"},"_id":"grunt-parallel@0.0.3","dist":{"shasum":"36156471693293dda9bc1bf0d63df3cd73642dce","tarball":"http://registry.npmjs.org/grunt-parallel/-/grunt-parallel-0.0.3.tgz"},"_npmVersion":"1.1.66","_npmUser":{"name":"iammerrick","email":"merrick.christensen@gmail.com"},"maintainers":[{"name":"iammerrick","email":"merrick.christensen@gmail.com"}],"directories":{}},"0.1.0":{"name":"grunt-parallel","description":"Run tasks or commands in child processes.","version":"0.1.0","homepage":"https://github.com/iammerrick/grunt-parallel","author":{"name":"Merrick Christensen","email":"merrick.christensen@gmail.com","url":"http://merrickchristensen.com"},"repository":{"type":"git","url":"git://github.com/iammerrick/grunt-parallel.git"},"bugs":{"url":"https://github.com/iammerrick/grunt-parallel/issues"},"licenses":[{"type":"MIT","url":"https://github.com/iammerrick/grunt-parallel/blob/master/LICENSE-MIT"}],"main":"Gruntfile.js","engines":{"node":"*"},"devDependencies":{"grunt":"~0.4.0"},"keywords":["gruntplugin","parallel"],"dependencies":{"q":"~0.8.12","grunt":"~0.4.1","lpad":"~0.1.0"},"_id":"grunt-parallel@0.1.0","dist":{"shasum":"fa2dd650bd3cca3acd7564a91756346473828520","tarball":"http://registry.npmjs.org/grunt-parallel/-/grunt-parallel-0.1.0.tgz"},"_from":".","_npmVersion":"1.2.18","_npmUser":{"name":"iammerrick","email":"merrick.christensen@gmail.com"},"maintainers":[{"name":"iammerrick","email":"merrick.christensen@gmail.com"}],"directories":{}},"0.2.0":{"name":"grunt-parallel","description":"Run tasks or commands in child processes.","version":"0.2.0","homepage":"https://github.com/iammerrick/grunt-parallel","author":{"name":"Merrick Christensen","email":"merrick.christensen@gmail.com","url":"http://merrickchristensen.com"},"repository":{"type":"git","url":"git://github.com/iammerrick/grunt-parallel.git"},"bugs":{"url":"https://github.com/iammerrick/grunt-parallel/issues"},"licenses":[{"type":"MIT","url":"https://github.com/iammerrick/grunt-parallel/blob/master/LICENSE-MIT"}],"main":"Gruntfile.js","engines":{"node":"*"},"peerDependencies":{"grunt":"~0.4.0"},"devDependencies":{"grunt":"~0.4.0"},"keywords":["gruntplugin","parallel"],"dependencies":{"q":"~0.8.12","grunt":"~0.4.1","lpad":"~0.1.0"},"_id":"grunt-parallel@0.2.0","dist":{"shasum":"7c7e296d33fc861416961454dcd3deb65211a28e","tarball":"http://registry.npmjs.org/grunt-parallel/-/grunt-parallel-0.2.0.tgz"},"_from":".","_npmVersion":"1.2.18","_npmUser":{"name":"iammerrick","email":"merrick.christensen@gmail.com"},"maintainers":[{"name":"iammerrick","email":"merrick.christensen@gmail.com"}],"directories":{}},"0.3.0":{"name":"grunt-parallel","description":"Run tasks or commands in child processes.","version":"0.3.0","homepage":"https://github.com/iammerrick/grunt-parallel","author":{"name":"Merrick Christensen","email":"merrick.christensen@gmail.com","url":"http://merrickchristensen.com"},"repository":{"type":"git","url":"git://github.com/iammerrick/grunt-parallel.git"},"bugs":{"url":"https://github.com/iammerrick/grunt-parallel/issues"},"licenses":[{"type":"MIT","url":"https://github.com/iammerrick/grunt-parallel/blob/master/LICENSE-MIT"}],"main":"Gruntfile.js","engines":{"node":"*"},"peerDependencies":{"grunt":"~0.4.0"},"devDependencies":{"grunt":"~0.4.0"},"keywords":["gruntplugin","parallel"],"dependencies":{"q":"~0.8.12","grunt":"~0.4.1","lpad":"~0.1.0"},"_id":"grunt-parallel@0.3.0","dist":{"shasum":"c46bb677c7281154743d3af3b4c783fc837b254e","tarball":"http://registry.npmjs.org/grunt-parallel/-/grunt-parallel-0.3.0.tgz"},"_from":".","_npmVersion":"1.3.5","_npmUser":{"name":"iammerrick","email":"merrick.christensen@gmail.com"},"maintainers":[{"name":"iammerrick","email":"merrick.christensen@gmail.com"}],"directories":{}},"0.3.1":{"name":"grunt-parallel","description":"Run tasks or commands in child processes.","version":"0.3.1","homepage":"https://github.com/iammerrick/grunt-parallel","author":{"name":"Merrick Christensen","email":"merrick.christensen@gmail.com","url":"http://merrickchristensen.com"},"repository":{"type":"git","url":"git://github.com/iammerrick/grunt-parallel.git"},"bugs":{"url":"https://github.com/iammerrick/grunt-parallel/issues"},"licenses":[{"type":"MIT","url":"https://github.com/iammerrick/grunt-parallel/blob/master/LICENSE-MIT"}],"main":"Gruntfile.js","engines":{"node":"*"},"peerDependencies":{"grunt":"~0.4.0"},"devDependencies":{"grunt":"~0.4.0"},"keywords":["gruntplugin","parallel"],"dependencies":{"q":"~0.8.12","grunt":"~0.4.1","lpad":"~0.1.0"},"_id":"grunt-parallel@0.3.1","dist":{"shasum":"9d11a2872b44a7bba0ec816f03388a15fa564663","tarball":"http://registry.npmjs.org/grunt-parallel/-/grunt-parallel-0.3.1.tgz"},"_from":".","_npmVersion":"1.3.8","_npmUser":{"name":"iammerrick","email":"merrick.christensen@gmail.com"},"maintainers":[{"name":"iammerrick","email":"merrick.christensen@gmail.com"}],"directories":{}},"0.4.0":{"name":"grunt-parallel","description":"Run tasks or commands in child processes.","version":"0.4.0","homepage":"https://github.com/iammerrick/grunt-parallel","author":{"name":"Merrick Christensen","email":"merrick.christensen@gmail.com","url":"http://merrickchristensen.com"},"repository":{"type":"git","url":"git://github.com/iammerrick/grunt-parallel.git"},"bugs":{"url":"https://github.com/iammerrick/grunt-parallel/issues"},"licenses":[{"type":"MIT","url":"https://github.com/iammerrick/grunt-parallel/blob/master/LICENSE-MIT"}],"main":"Gruntfile.js","engines":{"node":"*"},"peerDependencies":{"grunt":"~0.4.0"},"devDependencies":{"grunt":"~0.4.0"},"keywords":["gruntplugin","parallel"],"dependencies":{"q":"~0.8.12","grunt":"~0.4.1","lpad":"~0.1.0"},"gitHead":"9f29c62a03e7896ae63f26fcf2842faac8bbea2e","_id":"grunt-parallel@0.4.0","scripts":{},"_shasum":"5f79c5137edd0c38d3357a3b50fdd65a9817e977","_from":".","_npmVersion":"2.2.0","_nodeVersion":"0.10.33","_npmUser":{"name":"iammerrick","email":"merrick.christensen@gmail.com"},"maintainers":[{"name":"iammerrick","email":"merrick.christensen@gmail.com"}],"dist":{"shasum":"5f79c5137edd0c38d3357a3b50fdd65a9817e977","tarball":"http://registry.npmjs.org/grunt-parallel/-/grunt-parallel-0.4.0.tgz"},"directories":{}},"0.4.1":{"name":"grunt-parallel","description":"Run tasks or commands in child processes.","version":"0.4.1","homepage":"https://github.com/iammerrick/grunt-parallel","author":{"name":"Merrick Christensen","email":"merrick.christensen@gmail.com","url":"http://merrickchristensen.com"},"repository":{"type":"git","url":"git://github.com/iammerrick/grunt-parallel.git"},"bugs":{"url":"https://github.com/iammerrick/grunt-parallel/issues"},"licenses":[{"type":"MIT","url":"https://github.com/iammerrick/grunt-parallel/blob/master/LICENSE-MIT"}],"main":"Gruntfile.js","engines":{"node":"*"},"peerDependencies":{"grunt":"~0.4.0"},"devDependencies":{"grunt":"~0.4.0"},"keywords":["gruntplugin","parallel"],"dependencies":{"q":"~0.8.12","grunt":"~0.4.1","lpad":"~0.1.0"},"gitHead":"7310df9cf37aecb544cb76b3cecdc47ab1260b69","_id":"grunt-parallel@0.4.1","scripts":{},"_shasum":"89eb1fa10cd1e5b03ccd0d185cf30ba70c30cdc8","_from":".","_npmVersion":"2.2.0","_nodeVersion":"0.10.33","_npmUser":{"name":"iammerrick","email":"merrick.christensen@gmail.com"},"maintainers":[{"name":"iammerrick","email":"merrick.christensen@gmail.com"}],"dist":{"shasum":"89eb1fa10cd1e5b03ccd0d185cf30ba70c30cdc8","tarball":"http://registry.npmjs.org/grunt-parallel/-/grunt-parallel-0.4.1.tgz"},"directories":{}}},"readme":"# grunt-parallel\n\nRun commands and tasks in parallel to speed up your build.\n\n## Getting Started\nInstall this grunt plugin next to your project's [Gruntfile.js gruntfile][getting_started] with: `npm install grunt-parallel --save-dev`\n\nThen add this line to your project's `Gruntfile.js` gruntfile:\n\n```javascript\ngrunt.loadNpmTasks('grunt-parallel');\n```\n\n[grunt]: http://gruntjs.com/\n[getting_started]: https://github.com/gruntjs/grunt/blob/master/docs/getting_started.md\n\n## Documentation\n\n## The Configuration\n\n```javascript\ngrunt.initConfig({\n    parallel: {\n      mix: {\n        tasks: [{\n          grunt: true,\n          args: ['fast']\n        }, {\n          grunt: true,\n          args: ['block']\n        }, {\n          cmd: 'pwd'\n        },{\n          grunt: true,\n          args: ['fast']\n       }]\n      },\n      shell: {\n        tasks: [{\n          cmd: 'whoami'\n        }]\n      },\n      grunt: {\n        options: {\n          grunt: true\n        },\n        tasks: ['fast', 'block', 'fast']\n      },\n      stream: {\n        options: {\n          stream: true\n        },\n        tasks: [ { cmd: 'tail', args: ['-f', '/var/log/system.log'] }]\n      }\n    }\n  });\n```\n\n## Example\n\n![Example](http://f.cl.ly/items/3e281L3X3h01293q3Z11/grunt-parallel.png)\n\n\n### Settings\n\n* <tt>tasks</tt> - An array of commands to run, each deferred to: http://gruntjs.com/api/grunt.util#grunt.util.spawn\n\n```javascript\ngrunt.initConfig({\n  parallel: {\n    assets: {\n      tasks: [{\n        grunt: true,\n        args: ['requirejs']\n      }, {\n        grunt: true,\n        args: ['compass']\n      },{\n        cmd: 'some-custom-shell-script.sh'\n      }]\n    }\n  }\n});\n```\n\n#### Streaming Log Output For Never Ending Tasks\n\nSometimes tasks don't end and consequently you don't want to wait to receive their output till they are done, because you would never see their output. Think of watching files or tailing logs. For this case you can set the stream option to true, and all of the tasks output will be logged to your console, this is letting the sub process inherit your stdio.\n\n```javascript\ngrunt.initConfig({\n  stream: {\n    options: {\n      stream: true\n    },\n    tasks: [{ cmd: 'tail', args: ['-f', '/var/log/system.log']}]\n  }\n});\n```\n\nSince tail runs till you send it a shutdown signal, you would like to stream the output to your stdio.\n\n#### Only Using Grunt\n\nIf you are only going to delegate to other grunt tasks you can simply put `grunt: true` in your tasks configuration and grunt-parallel will run them all using grunt.\n\n```javascript\ngrunt.initConfig({\n  parallel: {\n    assets: {\n      options: {\n        grunt: true\n      },\n      tasks: ['fast', 'block', 'fast']\n    }\n  }\n});\n```\n\nOne might target the task using `grunt parallel:assets`. This would run compass, requirejs, and a custom shell script at the same time, each logging to your console when they are done.\n\n## License\nCopyright (c) 2013 Merrick Christensen\nLicensed under the MIT license.\n","maintainers":[{"name":"iammerrick","email":"merrick.christensen@gmail.com"}],"time":{"modified":"2015-02-18T01:13:17.915Z","created":"2013-02-22T20:02:13.574Z","0.0.1":"2013-02-22T20:02:14.145Z","0.0.2":"2013-02-27T17:28:42.790Z","0.0.3":"2013-03-12T23:18:59.952Z","0.1.0":"2013-04-12T20:52:42.219Z","0.2.0":"2013-05-24T22:34:12.340Z","0.3.0":"2013-08-14T21:43:40.437Z","0.3.1":"2013-08-25T00:46:49.130Z","0.4.0":"2015-01-29T18:01:50.499Z","0.4.1":"2015-02-18T01:13:17.915Z"},"author":{"name":"Merrick Christensen","email":"merrick.christensen@gmail.com","url":"http://merrickchristensen.com"},"repository":{"type":"git","url":"git://github.com/iammerrick/grunt-parallel.git"},"homepage":"https://github.com/iammerrick/grunt-parallel","keywords":["gruntplugin","parallel"],"bugs":{"url":"https://github.com/iammerrick/grunt-parallel/issues"},"readmeFilename":"README.md","_attachments":{},"_etag":"\"5ZGE0PKBO0C9M5VKFHRXT24CF\""}